README.md
setup.cfg
setup.py
osmopy/__init__.py
osmopy/_transaction.py
osmopy/_typing.py
osmopy/_wallet.py
osmopy.egg-info/PKG-INFO
osmopy.egg-info/SOURCES.txt
osmopy.egg-info/dependency_links.txt
osmopy.egg-info/not-zip-safe
osmopy.egg-info/requires.txt
osmopy.egg-info/top_level.txt
osmopy/interfaces/__init__.py
osmopy/interfaces/any_pb2.py
osmopy/interfaces/coin_pb2.py
osmopy/interfaces/gogo_pb2.py
osmopy/interfaces/msg_send_pb2.py
osmopy/interfaces/pubkey_pb2.py
osmopy/interfaces/signing_pb2.py
osmopy/interfaces/tx_pb2.py