Metadata-Version: 2.1
Name: osmopy
Version: 0.0.2
Summary: Tools for Osmosis wallet management, offline transaction signing and broadcasting
Home-page: https://github.com/bro-n-bro/osmopy
Author: bro-n-bro-0
Author-email: 
License: MIT
Platform: UNKNOWN
